{
	"resultCode": "0",
	"resultData": {
		"data": {
			"rows": [
				{
					"cllx": "轻型厢式货车",
					"createBy": "wywdata",
					"createTime": 1521012676000,
					"creditCode": "91340000790136024X",
					"dybj": "未抵押",
					"hphm": "BUP168",
					"hpzl": "小型汽车",
					"id": "34020009010913",
					"isDeleted": "0",
					"jdczt": "正常",
					"qzbfqz": 1712718907000,
					"ssxz": null,
					"updateBy": "wywdata",
					"updateTime": 1525749610000,
					"zwpp": "福田牌",
					"zzg": "中国"
				},
				{
					"cllx": "小型普通客车",
					"createBy": "wywdata",
					"createTime": 1521012676000,
					"creditCode": "91340000790136024X",
					"dybj": "未抵押",
					"hphm": "BUP777",
					"hpzl": "小型汽车",
					"id": "34020010017397",
					"isDeleted": "0",
					"jdczt": "违法未处理",
					"qzbfqz": 4102329600000,
					"ssxz": null,
					"updateBy": "wywdata",
					"updateTime": 1525749610000,
					"zwpp": "奥德赛牌",
					"zzg": "中国"
				},
				{
					"cllx": "中型普通客车",
					"createBy": "wywdata",
					"createTime": 1521012676000,
					"creditCode": "91340000790136024X",
					"dybj": "未抵押",
					"hphm": "B50705",
					"hpzl": "大型汽车",
					"id": "34020013166221",
					"isDeleted": "0",
					"jdczt": "正常",
					"qzbfqz": 2003414400000,
					"ssxz": null,
					"updateBy": "wywdata",
					"updateTime": 1525749610000,
					"zwpp": "金龙牌",
					"zzg": "中国"
				},
				{
					"cllx": "小型普通客车",
					"createBy": "wywdata",
					"createTime": 1521012676000,
					"creditCode": "91340000790136024X",
					"dybj": "未抵押",
					"hphm": "BUP916",
					"hpzl": "小型汽车",
					"id": "34020010037468",
					"isDeleted": "0",
					"jdczt": "正常",
					"qzbfqz": 4102329600000,
					"ssxz": null,
					"updateBy": "wywdata",
					"updateTime": 1525749610000,
					"zwpp": "江淮牌",
					"zzg": "中国"
				},
				{
					"cllx": "轻型普通货车",
					"createBy": "wywdata",
					"createTime": 1521012676000,
					"creditCode": "91340000790136024X",
					"dybj": "未抵押",
					"hphm": "BUP718",
					"hpzl": "小型汽车",
					"id": "34020016382258",
					"isDeleted": "0",
					"jdczt": "正常",
					"qzbfqz": 1953907200000,
					"ssxz": null,
					"updateBy": "wywdata",
					"updateTime": 1525749610000,
					"zwpp": "长城牌",
					"zzg": "中国"
				},
				{
					"cllx": "小型面包车",
					"createBy": "wywdata",
					"createTime": 1521012676000,
					"creditCode": "91340000790136024X",
					"dybj": "未抵押",
					"hphm": "BUP998",
					"hpzl": "小型汽车",
					"id": "34020010033655",
					"isDeleted": "0",
					"jdczt": "正常",
					"qzbfqz": 4102329600000,
					"ssxz": null,
					"updateBy": "wywdata",
					"updateTime": 1525749610000,
					"zwpp": "五菱牌",
					"zzg": "中国"
				},
				{
					"cllx": "中型普通客车",
					"createBy": "wywdata",
					"createTime": 1521012676000,
					"creditCode": "91340000790136024X",
					"dybj": "未抵押",
					"hphm": "B12113",
					"hpzl": "大型汽车",
					"id": "34020009019972",
					"isDeleted": "0",
					"jdczt": "正常",
					"qzbfqz": 1875335794000,
					"ssxz": null,
					"updateBy": "wywdata",
					"updateTime": 1525749610000,
					"zwpp": "金龙牌",
					"zzg": "中国"
				}
			],
			"total": 7
		},
		"token": "eyJhbGciOiJIUzI1NiIsInR5cCI6IkpXVCJ9.eyJwcmluY2lwYWwiOiJhaXRpbWUiLCJleHAiOjE1MzY1MTY3MjAsImlhdCI6MTUzMDUxNjcyMH0.O-qww3k41rgLhQ0PQjsEAFcJp-2BL6ckPCk7SWtssso"
	},
	"resultListData": [],
	"resultMapData": {},
	"resultMsg": "查询成功"
}